[{"poolAddress":"0x24946bCbBd028D5ABb62ad9B635EB1b1a67AF668","liquidations":{"yvDAI":[{"priceUsd":1.06552338,"normalizedTotalLiquidationInKind":0,"normalizedTotalLiquidationUsd":0},{"priceUsd":1.0442129124,"normalizedTotalLiquidationInKind":1414468.6372951753,"normalizedTotalLiquidationUsd":1414326.5114865},{"priceUsd":1.0229024448,"normalizedTotalLiquidationInKind":2561672.3297667354,"normalizedTotalLiquidationUsd":2561414.9329310404},{"priceUsd":1.0015919772,"normalizedTotalLiquidationInKind":3094491.6278633582,"normalizedTotalLiquidationUsd":3094180.6933445903},{"priceUsd":0.9802815095999999,"normalizedTotalLiquidationInKind":3094491.6278633582,"normalizedTotalLiquidationUsd":3094180.6933445903},{"priceUsd":0.9589710419999999,"normalizedTotalLiquidationInKind":4193465.6459027105,"normalizedTotalLiquidationUsd":4193044.2864746107},{"priceUsd":0.9376605744,"normalizedTotalLiquidationInKind":4193465.6459027105,"normalizedTotalLiquidationUsd":4193044.2864746107},{"priceUsd":0.9163501068,"normalizedTotalLiquidationInKind":4193465.6459027105,"normalizedTotalLiquidationUsd":4193044.2864746107},{"priceUsd":0.8950396391999998,"normalizedTotalLiquidationInKind":4193465.6459027105,"normalizedTotalLiquidationUsd":4193044.2864746107},{"priceUsd":0.8737291715999999,"normalizedTotalLiquidationInKind":4193465.6459027105,"normalizedTotalLiquidationUsd":4193044.2864746107},{"priceUsd":0.852418704,"normalizedTotalLiquidationInKind":4193465.6459027105,"normalizedTotalLiquidationUsd":4193044.2864746107},{"priceUsd":0.7458663659999999,"normalizedTotalLiquidationInKind":4193465.6459027105,"normalizedTotalLiquidationUsd":4193044.2864746107},{"priceUsd":0.6393140279999999,"normalizedTotalLiquidationInKind":4193465.6459027105,"normalizedTotalLiquidationUsd":4193044.2864746107},{"priceUsd":0.53276169,"normalizedTotalLiquidationInKind":4193465.6459027105,"normalizedTotalLiquidationUsd":4193044.2864746107},{"priceUsd":0.426209352,"normalizedTotalLiquidationInKind":4193465.6459027105,"normalizedTotalLiquidationUsd":4193044.2864746107},{"priceUsd":0.31965701399999996,"normalizedTotalLiquidationInKind":4193465.6459027105,"normalizedTotalLiquidationUsd":4193044.2864746107},{"priceUsd":0.213104676,"normalizedTotalLiquidationInKind":4193465.6459027105,"normalizedTotalLiquidationUsd":4193044.2864746107},{"priceUsd":0.106552338,"normalizedTotalLiquidationInKind":4193465.6459027105,"normalizedTotalLiquidationUsd":4193044.2864746107},{"priceUsd":0,"normalizedTotalLiquidationInKind":4193465.6459027105,"normalizedTotalLiquidationUsd":4193044.2864746107}],"DAI":[{"priceUsd":0.99989952,"normalizedTotalLiquidationInKind":0,"normalizedTotalLiquidationUsd":0},{"priceUsd":1.199879424,"normalizedTotalLiquidationInKind":6611250.60151834,"normalizedTotalLiquidationUsd":7932703.56366948},{"priceUsd":1.399859328,"normalizedTotalLiquidationInKind":6611250.60151834,"normalizedTotalLiquidationUsd":9254820.824281061},{"priceUsd":1.599839232,"normalizedTotalLiquidationInKind":6611250.60151834,"normalizedTotalLiquidationUsd":10576938.08489264},{"priceUsd":1.7998191360000002,"normalizedTotalLiquidationInKind":6611250.60151834,"normalizedTotalLiquidationUsd":11899055.34550422},{"priceUsd":1.99979904,"normalizedTotalLiquidationInKind":6611250.60151834,"normalizedTotalLiquidationUsd":13221172.6061158},{"priceUsd":2.199778944,"normalizedTotalLiquidationInKind":6611250.60151834,"normalizedTotalLiquidationUsd":14543289.866727382},{"priceUsd":2.399758848,"normalizedTotalLiquidationInKind":6611250.60151834,"normalizedTotalLiquidationUsd":15865407.12733896},{"priceUsd":2.5997387520000004,"normalizedTotalLiquidationInKind":6611250.60151834,"normalizedTotalLiquidationUsd":17187524.38795054},{"priceUsd":2.799718656,"normalizedTotalLiquidationInKind":6611250.60151834,"normalizedTotalLiquidationUsd":18509641.648562122},{"priceUsd":2.99969856,"normalizedTotalLiquidationInKind":6611250.60151834,"normalizedTotalLiquidationUsd":19831758.9091737},{"priceUsd":3.99959808,"normalizedTotalLiquidationInKind":6611250.60151834,"normalizedTotalLiquidationUsd":26442345.2122316},{"priceUsd":4.9994976,"normalizedTotalLiquidationInKind":6611250.60151834,"normalizedTotalLiquidationUsd":33052931.515289504},{"priceUsd":5.99939712,"normalizedTotalLiquidationInKind":6611250.60151834,"normalizedTotalLiquidationUsd":39663517.8183474},{"priceUsd":6.999296640000001,"normalizedTotalLiquidationInKind":6611250.60151834,"normalizedTotalLiquidationUsd":46274104.121405296},{"priceUsd":7.99919616,"normalizedTotalLiquidationInKind":6611250.60151834,"normalizedTotalLiquidationUsd":52884690.4244632},{"priceUsd":8.99909568,"normalizedTotalLiquidationInKind":6611250.60151834,"normalizedTotalLiquidationUsd":59495276.7275211},{"priceUsd":9.9989952,"normalizedTotalLiquidationInKind":6611250.60151834,"normalizedTotalLiquidationUsd":66105863.03057901},{"priceUsd":10.998894720000001,"normalizedTotalLiquidationInKind":6611250.60151834,"normalizedTotalLiquidationUsd":72716449.33363691}],"WETH":[{"priceUsd":1652.0616,"normalizedTotalLiquidationInKind":0,"normalizedTotalLiquidationUsd":0},{"priceUsd":1486.85544,"normalizedTotalLiquidationInKind":0,"normalizedTotalLiquidationUsd":0},{"priceUsd":1321.64928,"normalizedTotalLiquidationInKind":0,"normalizedTotalLiquidationUsd":0},{"priceUsd":1156.44312,"normalizedTotalLiquidationInKind":0,"normalizedTotalLiquidationUsd":0},{"priceUsd":991.23696,"normalizedTotalLiquidationInKind":0,"normalizedTotalLiquidationUsd":0},{"priceUsd":826.0308,"normalizedTotalLiquidationInKind":0,"normalizedTotalLiquidationUsd":0},{"priceUsd":660.82464,"normalizedTotalLiquidationInKind":0,"normalizedTotalLiquidationUsd":0},{"priceUsd":495.61848,"normalizedTotalLiquidationInKind":0,"normalizedTotalLiquidationUsd":0},{"priceUsd":330.41232,"normalizedTotalLiquidationInKind":0,"normalizedTotalLiquidationUsd":0},{"priceUsd":165.20616,"normalizedTotalLiquidationInKind":0,"normalizedTotalLiquidationUsd":0},{"priceUsd":0,"normalizedTotalLiquidationInKind":0,"normalizedTotalLiquidationUsd":0}],"USDC":[{"priceUsd":1.00002195,"normalizedTotalLiquidationInKind":0,"normalizedTotalLiquidationUsd":0},{"priceUsd":0.980021511,"normalizedTotalLiquidationInKind":0,"normalizedTotalLiquidationUsd":0},{"priceUsd":0.960021072,"normalizedTotalLiquidationInKind":0,"normalizedTotalLiquidationUsd":0},{"priceUsd":0.9400206329999999,"normalizedTotalLiquidationInKind":0,"normalizedTotalLiquidationUsd":0},{"priceUsd":0.9200201940000001,"normalizedTotalLiquidationInKind":0,"normalizedTotalLiquidationUsd":0},{"priceUsd":0.9000197550000001,"normalizedTotalLiquidationInKind":0,"normalizedTotalLiquidationUsd":0},{"priceUsd":0.880019316,"normalizedTotalLiquidationInKind":0,"normalizedTotalLiquidationUsd":0},{"priceUsd":0.860018877,"normalizedTotalLiquidationInKind":0,"normalizedTotalLiquidationUsd":0},{"priceUsd":0.840018438,"normalizedTotalLiquidationInKind":0,"normalizedTotalLiquidationUsd":0},{"priceUsd":0.8200179989999999,"normalizedTotalLiquidationInKind":0,"normalizedTotalLiquidationUsd":0},{"priceUsd":0.8000175600000001,"normalizedTotalLiquidationInKind":0,"normalizedTotalLiquidationUsd":0},{"priceUsd":0.700015365,"normalizedTotalLiquidationInKind":0,"normalizedTotalLiquidationUsd":0},{"priceUsd":0.60001317,"normalizedTotalLiquidationInKind":0,"normalizedTotalLiquidationUsd":0},{"priceUsd":0.500010975,"normalizedTotalLiquidationInKind":0,"normalizedTotalLiquidationUsd":0},{"priceUsd":0.40000878000000006,"normalizedTotalLiquidationInKind":0,"normalizedTotalLiquidationUsd":0},{"priceUsd":0.300006585,"normalizedTotalLiquidationInKind":0,"normalizedTotalLiquidationUsd":0},{"priceUsd":0.20000439000000003,"normalizedTotalLiquidationInKind":0,"normalizedTotalLiquidationUsd":0},{"priceUsd":0.10000219500000002,"normalizedTotalLiquidationInKind":0,"normalizedTotalLiquidationUsd":0},{"priceUsd":0,"normalizedTotalLiquidationInKind":0,"normalizedTotalLiquidationUsd":0}],"stkcvxcrvPlain3andSUSD":[{"priceUsd":1.06442727,"normalizedTotalLiquidationInKind":0,"normalizedTotalLiquidationUsd":0},{"priceUsd":1.0431387246,"normalizedTotalLiquidationInKind":0,"normalizedTotalLiquidationUsd":0},{"priceUsd":1.0218501791999999,"normalizedTotalLiquidationInKind":0,"normalizedTotalLiquidationUsd":0},{"priceUsd":1.0005616337999998,"normalizedTotalLiquidationInKind":1214287.5579981676,"normalizedTotalLiquidationUsd":1214165.54638434},{"priceUsd":0.9792730883999999,"normalizedTotalLiquidationInKind":1214287.5579981676,"normalizedTotalLiquidationUsd":1214165.54638434},{"priceUsd":0.9579845429999999,"normalizedTotalLiquidationInKind":1214287.5579981676,"normalizedTotalLiquidationUsd":1214165.54638434},{"priceUsd":0.9366959975999999,"normalizedTotalLiquidationInKind":1214287.5579981676,"normalizedTotalLiquidationUsd":1214165.54638434},{"priceUsd":0.9154074522,"normalizedTotalLiquidationInKind":1214287.5579981676,"normalizedTotalLiquidationUsd":1214165.54638434},{"priceUsd":0.8941189068,"normalizedTotalLiquidationInKind":1214287.5579981676,"normalizedTotalLiquidationUsd":1214165.54638434},{"priceUsd":0.8728303613999999,"normalizedTotalLiquidationInKind":1214287.5579981676,"normalizedTotalLiquidationUsd":1214165.54638434},{"priceUsd":0.851541816,"normalizedTotalLiquidationInKind":1214287.5579981676,"normalizedTotalLiquidationUsd":1214165.54638434},{"priceUsd":0.7450990889999999,"normalizedTotalLiquidationInKind":1214287.5579981676,"normalizedTotalLiquidationUsd":1214165.54638434},{"priceUsd":0.638656362,"normalizedTotalLiquidationInKind":1214287.5579981676,"normalizedTotalLiquidationUsd":1214165.54638434},{"priceUsd":0.532213635,"normalizedTotalLiquidationInKind":1214287.5579981676,"normalizedTotalLiquidationUsd":1214165.54638434},{"priceUsd":0.425770908,"normalizedTotalLiquidationInKind":1214287.5579981676,"normalizedTotalLiquidationUsd":1214165.54638434},{"priceUsd":0.319328181,"normalizedTotalLiquidationInKind":1214287.5579981676,"normalizedTotalLiquidationUsd":1214165.54638434},{"priceUsd":0.212885454,"normalizedTotalLiquidationInKind":1214287.5579981676,"normalizedTotalLiquidationUsd":1214165.54638434},{"priceUsd":0.106442727,"normalizedTotalLiquidationInKind":1214287.5579981676,"normalizedTotalLiquidationUsd":1214165.54638434},{"priceUsd":0,"normalizedTotalLiquidationInKind":1214287.5579981676,"normalizedTotalLiquidationUsd":1214165.54638434}],"USDT":[{"priceUsd":0.99943,"normalizedTotalLiquidationInKind":0,"normalizedTotalLiquidationUsd":0},{"priceUsd":0.9794414,"normalizedTotalLiquidationInKind":0,"normalizedTotalLiquidationUsd":0},{"priceUsd":0.9594528,"normalizedTotalLiquidationInKind":0,"normalizedTotalLiquidationUsd":0},{"priceUsd":0.9394642,"normalizedTotalLiquidationInKind":0,"normalizedTotalLiquidationUsd":0},{"priceUsd":0.9194756000000001,"normalizedTotalLiquidationInKind":0,"normalizedTotalLiquidationUsd":0},{"priceUsd":0.899487,"normalizedTotalLiquidationInKind":0,"normalizedTotalLiquidationUsd":0},{"priceUsd":0.8794984,"normalizedTotalLiquidationInKind":0,"normalizedTotalLiquidationUsd":0},{"priceUsd":0.8595098,"normalizedTotalLiquidationInKind":0,"normalizedTotalLiquidationUsd":0},{"priceUsd":0.8395212,"normalizedTotalLiquidationInKind":0,"normalizedTotalLiquidationUsd":0},{"priceUsd":0.8195325999999999,"normalizedTotalLiquidationInKind":0,"normalizedTotalLiquidationUsd":0},{"priceUsd":0.799544,"normalizedTotalLiquidationInKind":0,"normalizedTotalLiquidationUsd":0},{"priceUsd":0.699601,"normalizedTotalLiquidationInKind":0,"normalizedTotalLiquidationUsd":0},{"priceUsd":0.599658,"normalizedTotalLiquidationInKind":0,"normalizedTotalLiquidationUsd":0},{"priceUsd":0.499715,"normalizedTotalLiquidationInKind":0,"normalizedTotalLiquidationUsd":0},{"priceUsd":0.399772,"normalizedTotalLiquidationInKind":0,"normalizedTotalLiquidationUsd":0},{"priceUsd":0.299829,"normalizedTotalLiquidationInKind":0,"normalizedTotalLiquidationUsd":0},{"priceUsd":0.199886,"normalizedTotalLiquidationInKind":0,"normalizedTotalLiquidationUsd":0},{"priceUsd":0.099943,"normalizedTotalLiquidationInKind":0,"normalizedTotalLiquidationUsd":0},{"priceUsd":0,"normalizedTotalLiquidationInKind":0,"normalizedTotalLiquidationUsd":0}],"3Crv":[{"priceUsd":1.02656864,"normalizedTotalLiquidationInKind":0,"normalizedTotalLiquidationUsd":0},{"priceUsd":1.0060372672,"normalizedTotalLiquidationInKind":0,"normalizedTotalLiquidationUsd":0},{"priceUsd":0.9855058944,"normalizedTotalLiquidationInKind":0,"normalizedTotalLiquidationUsd":0},{"priceUsd":0.9649745216,"normalizedTotalLiquidationInKind":0,"normalizedTotalLiquidationUsd":0},{"priceUsd":0.9444431488,"normalizedTotalLiquidationInKind":0,"normalizedTotalLiquidationUsd":0},{"priceUsd":0.9239117760000001,"normalizedTotalLiquidationInKind":0,"normalizedTotalLiquidationUsd":0},{"priceUsd":0.9033804032,"normalizedTotalLiquidationInKind":0,"normalizedTotalLiquidationUsd":0},{"priceUsd":0.8828490304000001,"normalizedTotalLiquidationInKind":0,"normalizedTotalLiquidationUsd":0},{"priceUsd":0.8623176576,"normalizedTotalLiquidationInKind":0,"normalizedTotalLiquidationUsd":0},{"priceUsd":0.8417862848,"normalizedTotalLiquidationInKind":0,"normalizedTotalLiquidationUsd":0},{"priceUsd":0.8212549120000001,"normalizedTotalLiquidationInKind":0,"normalizedTotalLiquidationUsd":0},{"priceUsd":0.7185980479999999,"normalizedTotalLiquidationInKind":0,"normalizedTotalLiquidationUsd":0},{"priceUsd":0.615941184,"normalizedTotalLiquidationInKind":0,"normalizedTotalLiquidationUsd":0},{"priceUsd":0.51328432,"normalizedTotalLiquidationInKind":0,"normalizedTotalLiquidationUsd":0},{"priceUsd":0.41062745600000006,"normalizedTotalLiquidationInKind":0,"normalizedTotalLiquidationUsd":0},{"priceUsd":0.307970592,"normalizedTotalLiquidationInKind":0,"normalizedTotalLiquidationUsd":0},{"priceUsd":0.20531372800000003,"normalizedTotalLiquidationInKind":0,"normalizedTotalLiquidationUsd":0},{"priceUsd":0.10265686400000001,"normalizedTotalLiquidationInKind":0,"normalizedTotalLiquidationUsd":0},{"priceUsd":0,"normalizedTotalLiquidationInKind":0,"normalizedTotalLiquidationUsd":0}],"FRAX3CRV-f":[{"priceUsd":1.00963249,"normalizedTotalLiquidationInKind":0,"normalizedTotalLiquidationUsd":0},{"priceUsd":0.9894398402,"normalizedTotalLiquidationInKind":0,"normalizedTotalLiquidationUsd":0},{"priceUsd":0.9692471904,"normalizedTotalLiquidationInKind":0,"normalizedTotalLiquidationUsd":0},{"priceUsd":0.9490545405999999,"normalizedTotalLiquidationInKind":0,"normalizedTotalLiquidationUsd":0},{"priceUsd":0.9288618908,"normalizedTotalLiquidationInKind":0,"normalizedTotalLiquidationUsd":0},{"priceUsd":0.908669241,"normalizedTotalLiquidationInKind":0,"normalizedTotalLiquidationUsd":0},{"priceUsd":0.8884765912,"normalizedTotalLiquidationInKind":0,"normalizedTotalLiquidationUsd":0},{"priceUsd":0.8682839414,"normalizedTotalLiquidationInKind":0,"normalizedTotalLiquidationUsd":0},{"priceUsd":0.8480912916,"normalizedTotalLiquidationInKind":0,"normalizedTotalLiquidationUsd":0},{"priceUsd":0.8278986418,"normalizedTotalLiquidationInKind":0,"normalizedTotalLiquidationUsd":0},{"priceUsd":0.807705992,"normalizedTotalLiquidationInKind":0,"normalizedTotalLiquidationUsd":0},{"priceUsd":0.706742743,"normalizedTotalLiquidationInKind":0,"normalizedTotalLiquidationUsd":0},{"priceUsd":0.605779494,"normalizedTotalLiquidationInKind":0,"normalizedTotalLiquidationUsd":0},{"priceUsd":0.504816245,"normalizedTotalLiquidationInKind":0,"normalizedTotalLiquidationUsd":0},{"priceUsd":0.403852996,"normalizedTotalLiquidationInKind":0,"normalizedTotalLiquidationUsd":0},{"priceUsd":0.302889747,"normalizedTotalLiquidationInKind":0,"normalizedTotalLiquidationUsd":0},{"priceUsd":0.201926498,"normalizedTotalLiquidationInKind":0,"normalizedTotalLiquidationUsd":0},{"priceUsd":0.100963249,"normalizedTotalLiquidationInKind":0,"normalizedTotalLiquidationUsd":0},{"priceUsd":0,"normalizedTotalLiquidationInKind":0,"normalizedTotalLiquidationUsd":0}],"CVX":[{"priceUsd":2.75738641,"normalizedTotalLiquidationInKind":0,"normalizedTotalLiquidationUsd":0},{"priceUsd":2.4816477690000003,"normalizedTotalLiquidationInKind":0,"normalizedTotalLiquidationUsd":0},{"priceUsd":2.205909128,"normalizedTotalLiquidationInKind":0,"normalizedTotalLiquidationUsd":0},{"priceUsd":1.9301704869999998,"normalizedTotalLiquidationInKind":0,"normalizedTotalLiquidationUsd":0},{"priceUsd":1.654431846,"normalizedTotalLiquidationInKind":0,"normalizedTotalLiquidationUsd":0},{"priceUsd":1.378693205,"normalizedTotalLiquidationInKind":0,"normalizedTotalLiquidationUsd":0},{"priceUsd":1.102954564,"normalizedTotalLiquidationInKind":0,"normalizedTotalLiquidationUsd":0},{"priceUsd":0.827215923,"normalizedTotalLiquidationInKind":0,"normalizedTotalLiquidationUsd":0},{"priceUsd":0.551477282,"normalizedTotalLiquidationInKind":0,"normalizedTotalLiquidationUsd":0},{"priceUsd":0.275738641,"normalizedTotalLiquidationInKind":0,"normalizedTotalLiquidationUsd":0},{"priceUsd":0,"normalizedTotalLiquidationInKind":0,"normalizedTotalLiquidationUsd":0}],"FXS":[{"priceUsd":6.01940449,"normalizedTotalLiquidationInKind":0,"normalizedTotalLiquidationUsd":0},{"priceUsd":5.417464041000001,"normalizedTotalLiquidationInKind":0,"normalizedTotalLiquidationUsd":0},{"priceUsd":4.815523592000001,"normalizedTotalLiquidationInKind":0,"normalizedTotalLiquidationUsd":0},{"priceUsd":4.213583143,"normalizedTotalLiquidationInKind":0,"normalizedTotalLiquidationUsd":0},{"priceUsd":3.611642694,"normalizedTotalLiquidationInKind":0,"normalizedTotalLiquidationUsd":0},{"priceUsd":3.009702245,"normalizedTotalLiquidationInKind":0,"normalizedTotalLiquidationUsd":0},{"priceUsd":2.4077617960000004,"normalizedTotalLiquidationInKind":0,"normalizedTotalLiquidationUsd":0},{"priceUsd":1.805821347,"normalizedTotalLiquidationInKind":0,"normalizedTotalLiquidationUsd":0},{"priceUsd":1.2038808980000002,"normalizedTotalLiquidationInKind":0,"normalizedTotalLiquidationUsd":0},{"priceUsd":0.6019404490000001,"normalizedTotalLiquidationInKind":0,"normalizedTotalLiquidationUsd":0},{"priceUsd":0,"normalizedTotalLiquidationInKind":0,"normalizedTotalLiquidationUsd":0}],"stkcvxLUSD3CRV-f":[{"priceUsd":1.024671,"normalizedTotalLiquidationInKind":0,"normalizedTotalLiquidationUsd":0},{"priceUsd":1.0041775800000001,"normalizedTotalLiquidationInKind":0,"normalizedTotalLiquidationUsd":0},{"priceUsd":0.98368416,"normalizedTotalLiquidationInKind":0,"normalizedTotalLiquidationUsd":0},{"priceUsd":0.96319074,"normalizedTotalLiquidationInKind":0,"normalizedTotalLiquidationUsd":0},{"priceUsd":0.9426973200000002,"normalizedTotalLiquidationInKind":744947.1977270776,"normalizedTotalLiquidationUsd":744872.3454326501},{"priceUsd":0.9222039000000001,"normalizedTotalLiquidationInKind":744947.1977270776,"normalizedTotalLiquidationUsd":744872.3454326501},{"priceUsd":0.9017104800000001,"normalizedTotalLiquidationInKind":744947.1977270776,"normalizedTotalLiquidationUsd":744872.3454326501},{"priceUsd":0.8812170600000001,"normalizedTotalLiquidationInKind":744947.1977270776,"normalizedTotalLiquidationUsd":744872.3454326501},{"priceUsd":0.86072364,"normalizedTotalLiquidationInKind":744947.1977270776,"normalizedTotalLiquidationUsd":744872.3454326501},{"priceUsd":0.84023022,"normalizedTotalLiquidationInKind":744947.1977270776,"normalizedTotalLiquidationUsd":744872.3454326501},{"priceUsd":0.8197368000000002,"normalizedTotalLiquidationInKind":744947.1977270776,"normalizedTotalLiquidationUsd":744872.3454326501},{"priceUsd":0.7172697,"normalizedTotalLiquidationInKind":744947.1977270776,"normalizedTotalLiquidationUsd":744872.3454326501},{"priceUsd":0.6148026000000001,"normalizedTotalLiquidationInKind":744947.1977270776,"normalizedTotalLiquidationUsd":744872.3454326501},{"priceUsd":0.5123355,"normalizedTotalLiquidationInKind":744947.1977270776,"normalizedTotalLiquidationUsd":744872.3454326501},{"priceUsd":0.4098684000000001,"normalizedTotalLiquidationInKind":744947.1977270776,"normalizedTotalLiquidationUsd":744872.3454326501},{"priceUsd":0.30740130000000004,"normalizedTotalLiquidationInKind":744947.1977270776,"normalizedTotalLiquidationUsd":744872.3454326501},{"priceUsd":0.20493420000000004,"normalizedTotalLiquidationInKind":744947.1977270776,"normalizedTotalLiquidationUsd":744872.3454326501},{"priceUsd":0.10246710000000002,"normalizedTotalLiquidationInKind":744947.1977270776,"normalizedTotalLiquidationUsd":744872.3454326501},{"priceUsd":0,"normalizedTotalLiquidationInKind":744947.1977270776,"normalizedTotalLiquidationUsd":744872.3454326501}],"stkcvxgusd3CRV":[{"priceUsd":1.03815539,"normalizedTotalLiquidationInKind":0,"normalizedTotalLiquidationUsd":0},{"priceUsd":1.0173922821999999,"normalizedTotalLiquidationInKind":0,"normalizedTotalLiquidationUsd":0},{"priceUsd":0.9966291744,"normalizedTotalLiquidationInKind":0,"normalizedTotalLiquidationUsd":0},{"priceUsd":0.9758660666,"normalizedTotalLiquidationInKind":0,"normalizedTotalLiquidationUsd":0},{"priceUsd":0.9551029588000001,"normalizedTotalLiquidationInKind":0,"normalizedTotalLiquidationUsd":0},{"priceUsd":0.934339851,"normalizedTotalLiquidationInKind":0,"normalizedTotalLiquidationUsd":0},{"priceUsd":0.9135767432,"normalizedTotalLiquidationInKind":458550.199890385,"normalizedTotalLiquidationUsd":458504.1247663},{"priceUsd":0.8928136354,"normalizedTotalLiquidationInKind":458550.199890385,"normalizedTotalLiquidationUsd":458504.1247663},{"priceUsd":0.8720505276,"normalizedTotalLiquidationInKind":458550.199890385,"normalizedTotalLiquidationUsd":458504.1247663},{"priceUsd":0.8512874198,"normalizedTotalLiquidationInKind":458550.199890385,"normalizedTotalLiquidationUsd":458504.1247663},{"priceUsd":0.8305243120000001,"normalizedTotalLiquidationInKind":458550.199890385,"normalizedTotalLiquidationUsd":458504.1247663},{"priceUsd":0.7267087729999999,"normalizedTotalLiquidationInKind":458550.199890385,"normalizedTotalLiquidationUsd":458504.1247663},{"priceUsd":0.622893234,"normalizedTotalLiquidationInKind":458550.199890385,"normalizedTotalLiquidationUsd":458504.1247663},{"priceUsd":0.519077695,"normalizedTotalLiquidationInKind":458550.199890385,"normalizedTotalLiquidationUsd":458504.1247663},{"priceUsd":0.41526215600000005,"normalizedTotalLiquidationInKind":458550.199890385,"normalizedTotalLiquidationUsd":458504.1247663},{"priceUsd":0.311446617,"normalizedTotalLiquidationInKind":458550.199890385,"normalizedTotalLiquidationUsd":458504.1247663},{"priceUsd":0.20763107800000002,"normalizedTotalLiquidationInKind":458550.199890385,"normalizedTotalLiquidationUsd":458504.1247663},{"priceUsd":0.10381553900000001,"normalizedTotalLiquidationInKind":458550.199890385,"normalizedTotalLiquidationUsd":458504.1247663},{"priceUsd":0,"normalizedTotalLiquidationInKind":458550.199890385,"normalizedTotalLiquidationUsd":458504.1247663}]}},{"poolAddress":"0x86130bDD69143D8a4E5fc50bf4323D48049E98E4","liquidations":{"USDC":[{"priceUsd":1.00002195,"normalizedTotalLiquidationInKind":0,"normalizedTotalLiquidationUsd":0},{"priceUsd":1.20002634,"normalizedTotalLiquidationInKind":3118945.692753,"normalizedTotalLiquidationUsd":3742816.9843331473},{"priceUsd":1.40003073,"normalizedTotalLiquidationInKind":3540055.156994,"normalizedTotalLiquidationUsd":4956186.005686574},{"priceUsd":1.6000351200000003,"normalizedTotalLiquidationInKind":3540055.156994,"normalizedTotalLiquidationUsd":5664212.577927515},{"priceUsd":1.8000395100000002,"normalizedTotalLiquidationInKind":3540055.156994,"normalizedTotalLiquidationUsd":6372239.150168453},{"priceUsd":2.0000439,"normalizedTotalLiquidationInKind":3540055.156994,"normalizedTotalLiquidationUsd":7080265.722409392},{"priceUsd":2.2000482900000002,"normalizedTotalLiquidationInKind":3540055.156994,"normalizedTotalLiquidationUsd":7788292.294650333},{"priceUsd":2.40005268,"normalizedTotalLiquidationInKind":3540055.156994,"normalizedTotalLiquidationUsd":8496318.86689127},{"priceUsd":2.60005707,"normalizedTotalLiquidationInKind":3540055.156994,"normalizedTotalLiquidationUsd":9204345.439132212},{"priceUsd":2.80006146,"normalizedTotalLiquidationInKind":3540055.156994,"normalizedTotalLiquidationUsd":9912372.011373147},{"priceUsd":3.0000658500000004,"normalizedTotalLiquidationInKind":3540055.156994,"normalizedTotalLiquidationUsd":10620398.58361409},{"priceUsd":4.0000878,"normalizedTotalLiquidationInKind":3540055.156994,"normalizedTotalLiquidationUsd":14160531.444818784},{"priceUsd":5.00010975,"normalizedTotalLiquidationInKind":3540055.156994,"normalizedTotalLiquidationUsd":17700664.306023482},{"priceUsd":6.000131700000001,"normalizedTotalLiquidationInKind":3540055.156994,"normalizedTotalLiquidationUsd":21240797.16722818},{"priceUsd":7.000153650000001,"normalizedTotalLiquidationInKind":3540055.156994,"normalizedTotalLiquidationUsd":24780930.028432876},{"priceUsd":8.0001756,"normalizedTotalLiquidationInKind":3540055.156994,"normalizedTotalLiquidationUsd":28321062.889637567},{"priceUsd":9.000197550000001,"normalizedTotalLiquidationInKind":3540055.156994,"normalizedTotalLiquidationUsd":31861195.75084227},{"priceUsd":10.0002195,"normalizedTotalLiquidationInKind":3540055.156994,"normalizedTotalLiquidationUsd":35401328.612046964},{"priceUsd":11.00024145,"normalizedTotalLiquidationInKind":3540055.156994,"normalizedTotalLiquidationUsd":38941461.473251656}],"WETH":[{"priceUsd":1652.0616,"normalizedTotalLiquidationInKind":0,"normalizedTotalLiquidationUsd":0},{"priceUsd":1486.85544,"normalizedTotalLiquidationInKind":0,"normalizedTotalLiquidationUsd":0},{"priceUsd":1321.64928,"normalizedTotalLiquidationInKind":0,"normalizedTotalLiquidationUsd":0},{"priceUsd":1156.44312,"normalizedTotalLiquidationInKind":0,"normalizedTotalLiquidationUsd":0},{"priceUsd":991.23696,"normalizedTotalLiquidationInKind":0,"normalizedTotalLiquidationUsd":0},{"priceUsd":826.0308,"normalizedTotalLiquidationInKind":0,"normalizedTotalLiquidationUsd":0},{"priceUsd":660.82464,"normalizedTotalLiquidationInKind":421109.464241,"normalizedTotalLiquidationUsd":421118.70759374014},{"priceUsd":495.61848,"normalizedTotalLiquidationInKind":421109.464241,"normalizedTotalLiquidationUsd":421118.70759374014},{"priceUsd":330.41232,"normalizedTotalLiquidationInKind":421109.464241,"normalizedTotalLiquidationUsd":421118.70759374014},{"priceUsd":165.20616,"normalizedTotalLiquidationInKind":421109.464241,"normalizedTotalLiquidationUsd":421118.70759374014},{"priceUsd":0,"normalizedTotalLiquidationInKind":421109.464241,"normalizedTotalLiquidationUsd":421118.70759374014}],"WBTC":[{"priceUsd":26086.70279768,"normalizedTotalLiquidationInKind":0,"normalizedTotalLiquidationUsd":0},{"priceUsd":23478.032517911997,"normalizedTotalLiquidationInKind":0,"normalizedTotalLiquidationUsd":0},{"priceUsd":20869.362238144,"normalizedTotalLiquidationInKind":0,"normalizedTotalLiquidationUsd":0},{"priceUsd":18260.691958376,"normalizedTotalLiquidationInKind":0,"normalizedTotalLiquidationUsd":0},{"priceUsd":15652.021678607998,"normalizedTotalLiquidationInKind":0,"normalizedTotalLiquidationUsd":0},{"priceUsd":13043.35139884,"normalizedTotalLiquidationInKind":0,"normalizedTotalLiquidationUsd":0},{"priceUsd":10434.681119072,"normalizedTotalLiquidationInKind":421109.464241,"normalizedTotalLiquidationUsd":421118.70759374014},{"priceUsd":7826.010839303999,"normalizedTotalLiquidationInKind":421109.464241,"normalizedTotalLiquidationUsd":421118.70759374014},{"priceUsd":5217.340559536,"normalizedTotalLiquidationInKind":421109.464241,"normalizedTotalLiquidationUsd":421118.70759374014},{"priceUsd":2608.670279768,"normalizedTotalLiquidationInKind":421109.464241,"normalizedTotalLiquidationUsd":421118.70759374014},{"priceUsd":0,"normalizedTotalLiquidationInKind":421109.464241,"normalizedTotalLiquidationUsd":421118.70759374014}],"FRAX":[{"priceUsd":0.99832655,"normalizedTotalLiquidationInKind":0,"normalizedTotalLiquidationUsd":0},{"priceUsd":0.978360019,"normalizedTotalLiquidationInKind":0,"normalizedTotalLiquidationUsd":0},{"priceUsd":0.958393488,"normalizedTotalLiquidationInKind":0,"normalizedTotalLiquidationUsd":0},{"priceUsd":0.938426957,"normalizedTotalLiquidationInKind":0,"normalizedTotalLiquidationUsd":0},{"priceUsd":0.9184604260000001,"normalizedTotalLiquidationInKind":0,"normalizedTotalLiquidationUsd":0},{"priceUsd":0.8984938950000001,"normalizedTotalLiquidationInKind":0,"normalizedTotalLiquidationUsd":0},{"priceUsd":0.8785273640000001,"normalizedTotalLiquidationInKind":0,"normalizedTotalLiquidationUsd":0},{"priceUsd":0.858560833,"normalizedTotalLiquidationInKind":0,"normalizedTotalLiquidationUsd":0},{"priceUsd":0.838594302,"normalizedTotalLiquidationInKind":0,"normalizedTotalLiquidationUsd":0},{"priceUsd":0.818627771,"normalizedTotalLiquidationInKind":0,"normalizedTotalLiquidationUsd":0},{"priceUsd":0.79866124,"normalizedTotalLiquidationInKind":0,"normalizedTotalLiquidationUsd":0},{"priceUsd":0.698828585,"normalizedTotalLiquidationInKind":0,"normalizedTotalLiquidationUsd":0},{"priceUsd":0.59899593,"normalizedTotalLiquidationInKind":0,"normalizedTotalLiquidationUsd":0},{"priceUsd":0.499163275,"normalizedTotalLiquidationInKind":0,"normalizedTotalLiquidationUsd":0},{"priceUsd":0.39933062,"normalizedTotalLiquidationInKind":0,"normalizedTotalLiquidationUsd":0},{"priceUsd":0.299497965,"normalizedTotalLiquidationInKind":0,"normalizedTotalLiquidationUsd":0},{"priceUsd":0.19966531,"normalizedTotalLiquidationInKind":0,"normalizedTotalLiquidationUsd":0},{"priceUsd":0.099832655,"normalizedTotalLiquidationInKind":0,"normalizedTotalLiquidationUsd":0},{"priceUsd":0,"normalizedTotalLiquidationInKind":0,"normalizedTotalLiquidationUsd":0}],"FRAX3CRV-f":[{"priceUsd":1.00963249,"normalizedTotalLiquidationInKind":0,"normalizedTotalLiquidationUsd":0},{"priceUsd":0.9894398402,"normalizedTotalLiquidationInKind":0,"normalizedTotalLiquidationUsd":0},{"priceUsd":0.9692471904,"normalizedTotalLiquidationInKind":0,"normalizedTotalLiquidationUsd":0},{"priceUsd":0.9490545405999999,"normalizedTotalLiquidationInKind":0,"normalizedTotalLiquidationUsd":0},{"priceUsd":0.9288618908,"normalizedTotalLiquidationInKind":0,"normalizedTotalLiquidationUsd":0},{"priceUsd":0.908669241,"normalizedTotalLiquidationInKind":0,"normalizedTotalLiquidationUsd":0},{"priceUsd":0.8884765912,"normalizedTotalLiquidationInKind":0,"normalizedTotalLiquidationUsd":0},{"priceUsd":0.8682839414,"normalizedTotalLiquidationInKind":0,"normalizedTotalLiquidationUsd":0},{"priceUsd":0.8480912916,"normalizedTotalLiquidationInKind":0,"normalizedTotalLiquidationUsd":0},{"priceUsd":0.8278986418,"normalizedTotalLiquidationInKind":0,"normalizedTotalLiquidationUsd":0},{"priceUsd":0.807705992,"normalizedTotalLiquidationInKind":0,"normalizedTotalLiquidationUsd":0},{"priceUsd":0.706742743,"normalizedTotalLiquidationInKind":0,"normalizedTotalLiquidationUsd":0},{"priceUsd":0.605779494,"normalizedTotalLiquidationInKind":0,"normalizedTotalLiquidationUsd":0},{"priceUsd":0.504816245,"normalizedTotalLiquidationInKind":0,"normalizedTotalLiquidationUsd":0},{"priceUsd":0.403852996,"normalizedTotalLiquidationInKind":0,"normalizedTotalLiquidationUsd":0},{"priceUsd":0.302889747,"normalizedTotalLiquidationInKind":0,"normalizedTotalLiquidationUsd":0},{"priceUsd":0.201926498,"normalizedTotalLiquidationInKind":0,"normalizedTotalLiquidationUsd":0},{"priceUsd":0.100963249,"normalizedTotalLiquidationInKind":0,"normalizedTotalLiquidationUsd":0},{"priceUsd":0,"normalizedTotalLiquidationInKind":0,"normalizedTotalLiquidationUsd":0}],"CVX":[{"priceUsd":2.75738641,"normalizedTotalLiquidationInKind":0,"normalizedTotalLiquidationUsd":0},{"priceUsd":2.4816477690000003,"normalizedTotalLiquidationInKind":0,"normalizedTotalLiquidationUsd":0},{"priceUsd":2.205909128,"normalizedTotalLiquidationInKind":0,"normalizedTotalLiquidationUsd":0},{"priceUsd":1.9301704869999998,"normalizedTotalLiquidationInKind":0,"normalizedTotalLiquidationUsd":0},{"priceUsd":1.654431846,"normalizedTotalLiquidationInKind":0,"normalizedTotalLiquidationUsd":0},{"priceUsd":1.378693205,"normalizedTotalLiquidationInKind":0,"normalizedTotalLiquidationUsd":0},{"priceUsd":1.102954564,"normalizedTotalLiquidationInKind":0,"normalizedTotalLiquidationUsd":0},{"priceUsd":0.827215923,"normalizedTotalLiquidationInKind":0,"normalizedTotalLiquidationUsd":0},{"priceUsd":0.551477282,"normalizedTotalLiquidationInKind":0,"normalizedTotalLiquidationUsd":0},{"priceUsd":0.275738641,"normalizedTotalLiquidationInKind":0,"normalizedTotalLiquidationUsd":0},{"priceUsd":0,"normalizedTotalLiquidationInKind":0,"normalizedTotalLiquidationUsd":0}],"FXS":[{"priceUsd":6.01940449,"normalizedTotalLiquidationInKind":0,"normalizedTotalLiquidationUsd":0},{"priceUsd":5.417464041000001,"normalizedTotalLiquidationInKind":0,"normalizedTotalLiquidationUsd":0},{"priceUsd":4.815523592000001,"normalizedTotalLiquidationInKind":0,"normalizedTotalLiquidationUsd":0},{"priceUsd":4.213583143,"normalizedTotalLiquidationInKind":0,"normalizedTotalLiquidationUsd":0},{"priceUsd":3.611642694,"normalizedTotalLiquidationInKind":0,"normalizedTotalLiquidationUsd":0},{"priceUsd":3.009702245,"normalizedTotalLiquidationInKind":0,"normalizedTotalLiquidationUsd":0},{"priceUsd":2.4077617960000004,"normalizedTotalLiquidationInKind":0,"normalizedTotalLiquidationUsd":0},{"priceUsd":1.805821347,"normalizedTotalLiquidationInKind":0,"normalizedTotalLiquidationUsd":0},{"priceUsd":1.2038808980000002,"normalizedTotalLiquidationInKind":0,"normalizedTotalLiquidationUsd":0},{"priceUsd":0.6019404490000001,"normalizedTotalLiquidationInKind":0,"normalizedTotalLiquidationUsd":0},{"priceUsd":0,"normalizedTotalLiquidationInKind":0,"normalizedTotalLiquidationUsd":0}],"CRV":[{"priceUsd":0.44842016,"normalizedTotalLiquidationInKind":0,"normalizedTotalLiquidationUsd":0},{"priceUsd":0.403578144,"normalizedTotalLiquidationInKind":0,"normalizedTotalLiquidationUsd":0},{"priceUsd":0.35873612800000004,"normalizedTotalLiquidationInKind":0,"normalizedTotalLiquidationUsd":0},{"priceUsd":0.313894112,"normalizedTotalLiquidationInKind":0,"normalizedTotalLiquidationUsd":0},{"priceUsd":0.269052096,"normalizedTotalLiquidationInKind":0,"normalizedTotalLiquidationUsd":0},{"priceUsd":0.22421008,"normalizedTotalLiquidationInKind":0,"normalizedTotalLiquidationUsd":0},{"priceUsd":0.17936806400000002,"normalizedTotalLiquidationInKind":0,"normalizedTotalLiquidationUsd":0},{"priceUsd":0.134526048,"normalizedTotalLiquidationInKind":0,"normalizedTotalLiquidationUsd":0},{"priceUsd":0.08968403200000001,"normalizedTotalLiquidationInKind":0,"normalizedTotalLiquidationUsd":0},{"priceUsd":0.044842016000000005,"normalizedTotalLiquidationInKind":0,"normalizedTotalLiquidationUsd":0},{"priceUsd":0,"normalizedTotalLiquidationInKind":0,"normalizedTotalLiquidationUsd":0}],"3Crv":[{"priceUsd":1.02656864,"normalizedTotalLiquidationInKind":0,"normalizedTotalLiquidationUsd":0},{"priceUsd":1.0060372672,"normalizedTotalLiquidationInKind":0,"normalizedTotalLiquidationUsd":0},{"priceUsd":0.9855058944,"normalizedTotalLiquidationInKind":0,"normalizedTotalLiquidationUsd":0},{"priceUsd":0.9649745216,"normalizedTotalLiquidationInKind":0,"normalizedTotalLiquidationUsd":0},{"priceUsd":0.9444431488,"normalizedTotalLiquidationInKind":0,"normalizedTotalLiquidationUsd":0},{"priceUsd":0.9239117760000001,"normalizedTotalLiquidationInKind":0,"normalizedTotalLiquidationUsd":0},{"priceUsd":0.9033804032,"normalizedTotalLiquidationInKind":0,"normalizedTotalLiquidationUsd":0},{"priceUsd":0.8828490304000001,"normalizedTotalLiquidationInKind":0,"normalizedTotalLiquidationUsd":0},{"priceUsd":0.8623176576,"normalizedTotalLiquidationInKind":0,"normalizedTotalLiquidationUsd":0},{"priceUsd":0.8417862848,"normalizedTotalLiquidationInKind":0,"normalizedTotalLiquidationUsd":0},{"priceUsd":0.8212549120000001,"normalizedTotalLiquidationInKind":0,"normalizedTotalLiquidationUsd":0},{"priceUsd":0.7185980479999999,"normalizedTotalLiquidationInKind":0,"normalizedTotalLiquidationUsd":0},{"priceUsd":0.615941184,"normalizedTotalLiquidationInKind":0,"normalizedTotalLiquidationUsd":0},{"priceUsd":0.51328432,"normalizedTotalLiquidationInKind":0,"normalizedTotalLiquidationUsd":0},{"priceUsd":0.41062745600000006,"normalizedTotalLiquidationInKind":0,"normalizedTotalLiquidationUsd":0},{"priceUsd":0.307970592,"normalizedTotalLiquidationInKind":0,"normalizedTotalLiquidationUsd":0},{"priceUsd":0.20531372800000003,"normalizedTotalLiquidationInKind":0,"normalizedTotalLiquidationUsd":0},{"priceUsd":0.10265686400000001,"normalizedTotalLiquidationInKind":0,"normalizedTotalLiquidationUsd":0},{"priceUsd":0,"normalizedTotalLiquidationInKind":0,"normalizedTotalLiquidationUsd":0}],"stkcvxLUSD3CRV-f":[{"priceUsd":1.024671,"normalizedTotalLiquidationInKind":0,"normalizedTotalLiquidationUsd":0},{"priceUsd":1.0041775800000001,"normalizedTotalLiquidationInKind":0,"normalizedTotalLiquidationUsd":0},{"priceUsd":0.98368416,"normalizedTotalLiquidationInKind":0,"normalizedTotalLiquidationUsd":0},{"priceUsd":0.96319074,"normalizedTotalLiquidationInKind":1740586.3657010002,"normalizedTotalLiquidationUsd":1740624.5715717273},{"priceUsd":0.9426973200000002,"normalizedTotalLiquidationInKind":1740586.3657010002,"normalizedTotalLiquidationUsd":1740624.5715717273},{"priceUsd":0.9222039000000001,"normalizedTotalLiquidationInKind":1740586.3657010002,"normalizedTotalLiquidationUsd":1740624.5715717273},{"priceUsd":0.9017104800000001,"normalizedTotalLiquidationInKind":1740586.3657010002,"normalizedTotalLiquidationUsd":1740624.5715717273},{"priceUsd":0.8812170600000001,"normalizedTotalLiquidationInKind":1740586.3657010002,"normalizedTotalLiquidationUsd":1740624.5715717273},{"priceUsd":0.86072364,"normalizedTotalLiquidationInKind":1740586.3657010002,"normalizedTotalLiquidationUsd":1740624.5715717273},{"priceUsd":0.84023022,"normalizedTotalLiquidationInKind":1740586.3657010002,"normalizedTotalLiquidationUsd":1740624.5715717273},{"priceUsd":0.8197368000000002,"normalizedTotalLiquidationInKind":1740586.3657010002,"normalizedTotalLiquidationUsd":1740624.5715717273},{"priceUsd":0.7172697,"normalizedTotalLiquidationInKind":1740586.3657010002,"normalizedTotalLiquidationUsd":1740624.5715717273},{"priceUsd":0.6148026000000001,"normalizedTotalLiquidationInKind":1740586.3657010002,"normalizedTotalLiquidationUsd":1740624.5715717273},{"priceUsd":0.5123355,"normalizedTotalLiquidationInKind":1740586.3657010002,"normalizedTotalLiquidationUsd":1740624.5715717273},{"priceUsd":0.4098684000000001,"normalizedTotalLiquidationInKind":1740586.3657010002,"normalizedTotalLiquidationUsd":1740624.5715717273},{"priceUsd":0.30740130000000004,"normalizedTotalLiquidationInKind":1740586.3657010002,"normalizedTotalLiquidationUsd":1740624.5715717273},{"priceUsd":0.20493420000000004,"normalizedTotalLiquidationInKind":1740586.3657010002,"normalizedTotalLiquidationUsd":1740624.5715717273},{"priceUsd":0.10246710000000002,"normalizedTotalLiquidationInKind":1740586.3657010002,"normalizedTotalLiquidationUsd":1740624.5715717273},{"priceUsd":0,"normalizedTotalLiquidationInKind":1740586.3657010002,"normalizedTotalLiquidationUsd":1740624.5715717273}],"stkcvxcrvPlain3andSUSD":[{"priceUsd":1.06442727,"normalizedTotalLiquidationInKind":0,"normalizedTotalLiquidationUsd":0},{"priceUsd":1.0431387246,"normalizedTotalLiquidationInKind":0,"normalizedTotalLiquidationUsd":0},{"priceUsd":1.0218501791999999,"normalizedTotalLiquidationInKind":0,"normalizedTotalLiquidationUsd":0},{"priceUsd":1.0005616337999998,"normalizedTotalLiquidationInKind":0,"normalizedTotalLiquidationUsd":0},{"priceUsd":0.9792730883999999,"normalizedTotalLiquidationInKind":1210067.763865,"normalizedTotalLiquidationUsd":1210094.324852417},{"priceUsd":0.9579845429999999,"normalizedTotalLiquidationInKind":1210067.763865,"normalizedTotalLiquidationUsd":1210094.324852417},{"priceUsd":0.9366959975999999,"normalizedTotalLiquidationInKind":1210067.763865,"normalizedTotalLiquidationUsd":1210094.324852417},{"priceUsd":0.9154074522,"normalizedTotalLiquidationInKind":1210067.763865,"normalizedTotalLiquidationUsd":1210094.324852417},{"priceUsd":0.8941189068,"normalizedTotalLiquidationInKind":1210067.763865,"normalizedTotalLiquidationUsd":1210094.324852417},{"priceUsd":0.8728303613999999,"normalizedTotalLiquidationInKind":1210067.763865,"normalizedTotalLiquidationUsd":1210094.324852417},{"priceUsd":0.851541816,"normalizedTotalLiquidationInKind":1210067.763865,"normalizedTotalLiquidationUsd":1210094.324852417},{"priceUsd":0.7450990889999999,"normalizedTotalLiquidationInKind":1210067.763865,"normalizedTotalLiquidationUsd":1210094.324852417},{"priceUsd":0.638656362,"normalizedTotalLiquidationInKind":1210067.763865,"normalizedTotalLiquidationUsd":1210094.324852417},{"priceUsd":0.532213635,"normalizedTotalLiquidationInKind":1210067.763865,"normalizedTotalLiquidationUsd":1210094.324852417},{"priceUsd":0.425770908,"normalizedTotalLiquidationInKind":1210067.763865,"normalizedTotalLiquidationUsd":1210094.324852417},{"priceUsd":0.319328181,"normalizedTotalLiquidationInKind":1210067.763865,"normalizedTotalLiquidationUsd":1210094.324852417},{"priceUsd":0.212885454,"normalizedTotalLiquidationInKind":1210067.763865,"normalizedTotalLiquidationUsd":1210094.324852417},{"priceUsd":0.106442727,"normalizedTotalLiquidationInKind":1210067.763865,"normalizedTotalLiquidationUsd":1210094.324852417},{"priceUsd":0,"normalizedTotalLiquidationInKind":1210067.763865,"normalizedTotalLiquidationUsd":1210094.324852417}],"gusd3CRV":[{"priceUsd":1.03815539,"normalizedTotalLiquidationInKind":0,"normalizedTotalLiquidationUsd":0},{"priceUsd":1.0173922821999999,"normalizedTotalLiquidationInKind":0,"normalizedTotalLiquidationUsd":0},{"priceUsd":0.9966291744,"normalizedTotalLiquidationInKind":0,"normalizedTotalLiquidationUsd":0},{"priceUsd":0.9758660666,"normalizedTotalLiquidationInKind":0,"normalizedTotalLiquidationUsd":0},{"priceUsd":0.9551029588000001,"normalizedTotalLiquidationInKind":0,"normalizedTotalLiquidationUsd":0},{"priceUsd":0.934339851,"normalizedTotalLiquidationInKind":0,"normalizedTotalLiquidationUsd":0},{"priceUsd":0.9135767432,"normalizedTotalLiquidationInKind":0,"normalizedTotalLiquidationUsd":0},{"priceUsd":0.8928136354,"normalizedTotalLiquidationInKind":0,"normalizedTotalLiquidationUsd":0},{"priceUsd":0.8720505276,"normalizedTotalLiquidationInKind":0,"normalizedTotalLiquidationUsd":0},{"priceUsd":0.8512874198,"normalizedTotalLiquidationInKind":0,"normalizedTotalLiquidationUsd":0},{"priceUsd":0.8305243120000001,"normalizedTotalLiquidationInKind":0,"normalizedTotalLiquidationUsd":0},{"priceUsd":0.7267087729999999,"normalizedTotalLiquidationInKind":0,"normalizedTotalLiquidationUsd":0},{"priceUsd":0.622893234,"normalizedTotalLiquidationInKind":0,"normalizedTotalLiquidationUsd":0},{"priceUsd":0.519077695,"normalizedTotalLiquidationInKind":0,"normalizedTotalLiquidationUsd":0},{"priceUsd":0.41526215600000005,"normalizedTotalLiquidationInKind":0,"normalizedTotalLiquidationUsd":0},{"priceUsd":0.311446617,"normalizedTotalLiquidationInKind":0,"normalizedTotalLiquidationUsd":0},{"priceUsd":0.20763107800000002,"normalizedTotalLiquidationInKind":0,"normalizedTotalLiquidationUsd":0},{"priceUsd":0.10381553900000001,"normalizedTotalLiquidationInKind":0,"normalizedTotalLiquidationUsd":0},{"priceUsd":0,"normalizedTotalLiquidationInKind":0,"normalizedTotalLiquidationUsd":0}],"stkcvxFRAX3CRV-f":[{"priceUsd":1.00963249,"normalizedTotalLiquidationInKind":0,"normalizedTotalLiquidationUsd":0},{"priceUsd":0.9894398402,"normalizedTotalLiquidationInKind":0,"normalizedTotalLiquidationUsd":0},{"priceUsd":0.9692471904,"normalizedTotalLiquidationInKind":0,"normalizedTotalLiquidationUsd":0},{"priceUsd":0.9490545405999999,"normalizedTotalLiquidationInKind":168291.563187,"normalizedTotalLiquidationUsd":168295.25718681194},{"priceUsd":0.9288618908,"normalizedTotalLiquidationInKind":168291.563187,"normalizedTotalLiquidationUsd":168295.25718681194},{"priceUsd":0.908669241,"normalizedTotalLiquidationInKind":168291.563187,"normalizedTotalLiquidationUsd":168295.25718681194},{"priceUsd":0.8884765912,"normalizedTotalLiquidationInKind":168291.563187,"normalizedTotalLiquidationUsd":168295.25718681194},{"priceUsd":0.8682839414,"normalizedTotalLiquidationInKind":168291.563187,"normalizedTotalLiquidationUsd":168295.25718681194},{"priceUsd":0.8480912916,"normalizedTotalLiquidationInKind":168291.563187,"normalizedTotalLiquidationUsd":168295.25718681194},{"priceUsd":0.8278986418,"normalizedTotalLiquidationInKind":168291.563187,"normalizedTotalLiquidationUsd":168295.25718681194},{"priceUsd":0.807705992,"normalizedTotalLiquidationInKind":168291.563187,"normalizedTotalLiquidationUsd":168295.25718681194},{"priceUsd":0.706742743,"normalizedTotalLiquidationInKind":168291.563187,"normalizedTotalLiquidationUsd":168295.25718681194},{"priceUsd":0.605779494,"normalizedTotalLiquidationInKind":168291.563187,"normalizedTotalLiquidationUsd":168295.25718681194},{"priceUsd":0.504816245,"normalizedTotalLiquidationInKind":168291.563187,"normalizedTotalLiquidationUsd":168295.25718681194},{"priceUsd":0.403852996,"normalizedTotalLiquidationInKind":168291.563187,"normalizedTotalLiquidationUsd":168295.25718681194},{"priceUsd":0.302889747,"normalizedTotalLiquidationInKind":168291.563187,"normalizedTotalLiquidationUsd":168295.25718681194},{"priceUsd":0.201926498,"normalizedTotalLiquidationInKind":168291.563187,"normalizedTotalLiquidationUsd":168295.25718681194},{"priceUsd":0.100963249,"normalizedTotalLiquidationInKind":168291.563187,"normalizedTotalLiquidationUsd":168295.25718681194},{"priceUsd":0,"normalizedTotalLiquidationInKind":168291.563187,"normalizedTotalLiquidationUsd":168295.25718681194}]}},{"poolAddress":"0xB03670c20F87f2169A7c4eBE35746007e9575901","liquidations":{"WETH":[{"priceUsd":1652.0616,"normalizedTotalLiquidationInKind":0,"normalizedTotalLiquidationUsd":0},{"priceUsd":3304.1232,"normalizedTotalLiquidationInKind":6535.245664895322,"normalizedTotalLiquidationUsd":21593256.819080062},{"priceUsd":4956.1848,"normalizedTotalLiquidationInKind":6535.245664895322,"normalizedTotalLiquidationUsd":32389885.228620086},{"priceUsd":6608.2464,"normalizedTotalLiquidationInKind":6535.245664895322,"normalizedTotalLiquidationUsd":43186513.638160124},{"priceUsd":8260.308,"normalizedTotalLiquidationInKind":6535.245664895322,"normalizedTotalLiquidationUsd":53983142.04770016},{"priceUsd":9912.3696,"normalizedTotalLiquidationInKind":6535.245664895322,"normalizedTotalLiquidationUsd":64779770.45724017},{"priceUsd":11564.431199999999,"normalizedTotalLiquidationInKind":6535.245664895322,"normalizedTotalLiquidationUsd":75576398.8667802},{"priceUsd":13216.4928,"normalizedTotalLiquidationInKind":6535.245664895322,"normalizedTotalLiquidationUsd":86373027.27632025},{"priceUsd":14868.5544,"normalizedTotalLiquidationInKind":6535.245664895322,"normalizedTotalLiquidationUsd":97169655.68586025},{"priceUsd":16520.616,"normalizedTotalLiquidationInKind":6535.245664895322,"normalizedTotalLiquidationUsd":107966284.09540032},{"priceUsd":18172.6776,"normalizedTotalLiquidationInKind":6535.245664895322,"normalizedTotalLiquidationUsd":118762912.50494032}],"stETH":[{"priceUsd":1651.26105632,"normalizedTotalLiquidationInKind":0,"normalizedTotalLiquidationUsd":0},{"priceUsd":1486.1349506880001,"normalizedTotalLiquidationInKind":2245.5553202219335,"normalizedTotalLiquidationUsd":3709795.7152143596},{"priceUsd":1321.0088450560002,"normalizedTotalLiquidationInKind":6291.0394767325815,"normalizedTotalLiquidationUsd":10393184.743593989},{"priceUsd":1155.882739424,"normalizedTotalLiquidationInKind":6291.0394767325815,"normalizedTotalLiquidationUsd":10393184.743593989},{"priceUsd":990.756633792,"normalizedTotalLiquidationInKind":6291.0394767325815,"normalizedTotalLiquidationUsd":10393184.743593989},{"priceUsd":825.63052816,"normalizedTotalLiquidationInKind":6291.0394767325815,"normalizedTotalLiquidationUsd":10393184.743593989},{"priceUsd":660.5044225280001,"normalizedTotalLiquidationInKind":6291.0394767325815,"normalizedTotalLiquidationUsd":10393184.743593989},{"priceUsd":495.378316896,"normalizedTotalLiquidationInKind":6291.0394767325815,"normalizedTotalLiquidationUsd":10393184.743593989},{"priceUsd":330.25221126400004,"normalizedTotalLiquidationInKind":6291.0394767325815,"normalizedTotalLiquidationUsd":10393184.743593989},{"priceUsd":165.12610563200002,"normalizedTotalLiquidationInKind":6448.61193710231,"normalizedTotalLiquidationUsd":10653504.15458834},{"priceUsd":0,"normalizedTotalLiquidationInKind":6448.61193710231,"normalizedTotalLiquidationUsd":10653504.15458834}],"steCRV":[{"priceUsd":1781.55228122,"normalizedTotalLiquidationInKind":0,"normalizedTotalLiquidationUsd":0},{"priceUsd":1603.397053098,"normalizedTotalLiquidationInKind":0,"normalizedTotalLiquidationUsd":0},{"priceUsd":1425.241824976,"normalizedTotalLiquidationInKind":0,"normalizedTotalLiquidationUsd":0},{"priceUsd":1247.086596854,"normalizedTotalLiquidationInKind":0,"normalizedTotalLiquidationUsd":0},{"priceUsd":1068.931368732,"normalizedTotalLiquidationInKind":0,"normalizedTotalLiquidationUsd":0},{"priceUsd":890.77614061,"normalizedTotalLiquidationInKind":0,"normalizedTotalLiquidationUsd":0},{"priceUsd":712.620912488,"normalizedTotalLiquidationInKind":0,"normalizedTotalLiquidationUsd":0},{"priceUsd":534.465684366,"normalizedTotalLiquidationInKind":0,"normalizedTotalLiquidationUsd":0},{"priceUsd":356.310456244,"normalizedTotalLiquidationInKind":0,"normalizedTotalLiquidationUsd":0},{"priceUsd":178.155228122,"normalizedTotalLiquidationInKind":0,"normalizedTotalLiquidationUsd":0},{"priceUsd":0,"normalizedTotalLiquidationInKind":0,"normalizedTotalLiquidationUsd":0}],"CVX":[{"priceUsd":2.75738641,"normalizedTotalLiquidationInKind":0,"normalizedTotalLiquidationUsd":0},{"priceUsd":2.4816477690000003,"normalizedTotalLiquidationInKind":0,"normalizedTotalLiquidationUsd":0},{"priceUsd":2.205909128,"normalizedTotalLiquidationInKind":0,"normalizedTotalLiquidationUsd":0},{"priceUsd":1.9301704869999998,"normalizedTotalLiquidationInKind":0,"normalizedTotalLiquidationUsd":0},{"priceUsd":1.654431846,"normalizedTotalLiquidationInKind":0,"normalizedTotalLiquidationUsd":0},{"priceUsd":1.378693205,"normalizedTotalLiquidationInKind":0,"normalizedTotalLiquidationUsd":0},{"priceUsd":1.102954564,"normalizedTotalLiquidationInKind":0,"normalizedTotalLiquidationUsd":0},{"priceUsd":0.827215923,"normalizedTotalLiquidationInKind":0,"normalizedTotalLiquidationUsd":0},{"priceUsd":0.551477282,"normalizedTotalLiquidationInKind":0,"normalizedTotalLiquidationUsd":0},{"priceUsd":0.275738641,"normalizedTotalLiquidationInKind":0,"normalizedTotalLiquidationUsd":0},{"priceUsd":0,"normalizedTotalLiquidationInKind":0,"normalizedTotalLiquidationUsd":0}],"CRV":[{"priceUsd":0.44842016,"normalizedTotalLiquidationInKind":0,"normalizedTotalLiquidationUsd":0},{"priceUsd":0.403578144,"normalizedTotalLiquidationInKind":0,"normalizedTotalLiquidationUsd":0},{"priceUsd":0.35873612800000004,"normalizedTotalLiquidationInKind":0,"normalizedTotalLiquidationUsd":0},{"priceUsd":0.313894112,"normalizedTotalLiquidationInKind":0,"normalizedTotalLiquidationUsd":0},{"priceUsd":0.269052096,"normalizedTotalLiquidationInKind":0,"normalizedTotalLiquidationUsd":0},{"priceUsd":0.22421008,"normalizedTotalLiquidationInKind":0,"normalizedTotalLiquidationUsd":0},{"priceUsd":0.17936806400000002,"normalizedTotalLiquidationInKind":0,"normalizedTotalLiquidationUsd":0},{"priceUsd":0.134526048,"normalizedTotalLiquidationInKind":0,"normalizedTotalLiquidationUsd":0},{"priceUsd":0.08968403200000001,"normalizedTotalLiquidationInKind":0,"normalizedTotalLiquidationUsd":0},{"priceUsd":0.044842016000000005,"normalizedTotalLiquidationInKind":0,"normalizedTotalLiquidationUsd":0},{"priceUsd":0,"normalizedTotalLiquidationInKind":0,"normalizedTotalLiquidationUsd":0}],"yvWETH":[{"priceUsd":1721.03529065,"normalizedTotalLiquidationInKind":0,"normalizedTotalLiquidationUsd":0},{"priceUsd":1548.931761585,"normalizedTotalLiquidationInKind":86.63372779301329,"normalizedTotalLiquidationUsd":143124.25495169},{"priceUsd":1376.82823252,"normalizedTotalLiquidationInKind":86.63372779301329,"normalizedTotalLiquidationUsd":143124.25495169},{"priceUsd":1204.7247034549998,"normalizedTotalLiquidationInKind":86.63372779301329,"normalizedTotalLiquidationUsd":143124.25495169},{"priceUsd":1032.6211743899999,"normalizedTotalLiquidationInKind":86.63372779301329,"normalizedTotalLiquidationUsd":143124.25495169},{"priceUsd":860.517645325,"normalizedTotalLiquidationInKind":86.63372779301329,"normalizedTotalLiquidationUsd":143124.25495169},{"priceUsd":688.41411626,"normalizedTotalLiquidationInKind":86.63372779301329,"normalizedTotalLiquidationUsd":143124.25495169},{"priceUsd":516.3105871949999,"normalizedTotalLiquidationInKind":86.63372779301329,"normalizedTotalLiquidationUsd":143124.25495169},{"priceUsd":344.20705813,"normalizedTotalLiquidationInKind":86.63372779301329,"normalizedTotalLiquidationUsd":143124.25495169},{"priceUsd":172.103529065,"normalizedTotalLiquidationInKind":86.63372779301329,"normalizedTotalLiquidationUsd":143124.25495169},{"priceUsd":0,"normalizedTotalLiquidationInKind":86.63372779301329,"normalizedTotalLiquidationUsd":143124.25495169}],"USDC":[{"priceUsd":1.00002195,"normalizedTotalLiquidationInKind":0,"normalizedTotalLiquidationUsd":0},{"priceUsd":0.980021511,"normalizedTotalLiquidationInKind":0,"normalizedTotalLiquidationUsd":0},{"priceUsd":0.960021072,"normalizedTotalLiquidationInKind":0,"normalizedTotalLiquidationUsd":0},{"priceUsd":0.9400206329999999,"normalizedTotalLiquidationInKind":0,"normalizedTotalLiquidationUsd":0},{"priceUsd":0.9200201940000001,"normalizedTotalLiquidationInKind":0,"normalizedTotalLiquidationUsd":0},{"priceUsd":0.9000197550000001,"normalizedTotalLiquidationInKind":0,"normalizedTotalLiquidationUsd":0},{"priceUsd":0.880019316,"normalizedTotalLiquidationInKind":0,"normalizedTotalLiquidationUsd":0},{"priceUsd":0.860018877,"normalizedTotalLiquidationInKind":0,"normalizedTotalLiquidationUsd":0},{"priceUsd":0.840018438,"normalizedTotalLiquidationInKind":0,"normalizedTotalLiquidationUsd":0},{"priceUsd":0.8200179989999999,"normalizedTotalLiquidationInKind":0,"normalizedTotalLiquidationUsd":0},{"priceUsd":0.8000175600000001,"normalizedTotalLiquidationInKind":0,"normalizedTotalLiquidationUsd":0},{"priceUsd":0.700015365,"normalizedTotalLiquidationInKind":0,"normalizedTotalLiquidationUsd":0},{"priceUsd":0.60001317,"normalizedTotalLiquidationInKind":0,"normalizedTotalLiquidationUsd":0},{"priceUsd":0.500010975,"normalizedTotalLiquidationInKind":0,"normalizedTotalLiquidationUsd":0},{"priceUsd":0.40000878000000006,"normalizedTotalLiquidationInKind":0,"normalizedTotalLiquidationUsd":0},{"priceUsd":0.300006585,"normalizedTotalLiquidationInKind":0,"normalizedTotalLiquidationUsd":0},{"priceUsd":0.20000439000000003,"normalizedTotalLiquidationInKind":0,"normalizedTotalLiquidationUsd":0},{"priceUsd":0.10000219500000002,"normalizedTotalLiquidationInKind":157.57246036972833,"normalizedTotalLiquidationUsd":260319.41099434998},{"priceUsd":0,"normalizedTotalLiquidationInKind":157.57246036972833,"normalizedTotalLiquidationUsd":260319.41099434998}],"FRAX":[{"priceUsd":0.99832655,"normalizedTotalLiquidationInKind":0,"normalizedTotalLiquidationUsd":0},{"priceUsd":0.978360019,"normalizedTotalLiquidationInKind":0,"normalizedTotalLiquidationUsd":0},{"priceUsd":0.958393488,"normalizedTotalLiquidationInKind":0,"normalizedTotalLiquidationUsd":0},{"priceUsd":0.938426957,"normalizedTotalLiquidationInKind":0,"normalizedTotalLiquidationUsd":0},{"priceUsd":0.9184604260000001,"normalizedTotalLiquidationInKind":0,"normalizedTotalLiquidationUsd":0},{"priceUsd":0.8984938950000001,"normalizedTotalLiquidationInKind":0,"normalizedTotalLiquidationUsd":0},{"priceUsd":0.8785273640000001,"normalizedTotalLiquidationInKind":0,"normalizedTotalLiquidationUsd":0},{"priceUsd":0.858560833,"normalizedTotalLiquidationInKind":0,"normalizedTotalLiquidationUsd":0},{"priceUsd":0.838594302,"normalizedTotalLiquidationInKind":0,"normalizedTotalLiquidationUsd":0},{"priceUsd":0.818627771,"normalizedTotalLiquidationInKind":0,"normalizedTotalLiquidationUsd":0},{"priceUsd":0.79866124,"normalizedTotalLiquidationInKind":0,"normalizedTotalLiquidationUsd":0},{"priceUsd":0.698828585,"normalizedTotalLiquidationInKind":0,"normalizedTotalLiquidationUsd":0},{"priceUsd":0.59899593,"normalizedTotalLiquidationInKind":0,"normalizedTotalLiquidationUsd":0},{"priceUsd":0.499163275,"normalizedTotalLiquidationInKind":0,"normalizedTotalLiquidationUsd":0},{"priceUsd":0.39933062,"normalizedTotalLiquidationInKind":1090.7320808757072,"normalizedTotalLiquidationUsd":1801956.5867028502},{"priceUsd":0.299497965,"normalizedTotalLiquidationInKind":1090.7320808757072,"normalizedTotalLiquidationUsd":1801956.5867028502},{"priceUsd":0.19966531,"normalizedTotalLiquidationInKind":1090.7320808757072,"normalizedTotalLiquidationUsd":1801956.5867028502},{"priceUsd":0.099832655,"normalizedTotalLiquidationInKind":1090.7320808757072,"normalizedTotalLiquidationUsd":1801956.5867028502},{"priceUsd":0,"normalizedTotalLiquidationInKind":1090.7320808757072,"normalizedTotalLiquidationUsd":1801956.5867028502}]}},{"poolAddress":"0xB2A015c71c17bCAC6af36645DEad8c572bA08A08","liquidations":{}},{"poolAddress":"0xB8cf3Ed326bB0E51454361Fb37E9E8df6DC5C286","liquidations":{}},{"poolAddress":"0x79012c8d491DcF3A30Db20d1f449b14CAF01da6C","liquidations":{}}]