{"json_time": 1683622514, "ETH": {"oracle": 1841.756089999, "cex_price": 1839.475, "dex_price": 1849.7508294931279}, "BNB|bsc": {"oracle": 315.119041747, "cex_price": 315.05, "dex_price": 315.96707350199665}, "WBTC|eth": {"oracle": 27582.20166, "cex_price": 27560.275, "dex_price": 27149.692937783773}, "pCKB": {"oracle": 0.003129406, "cex_price": 0.003125, "dex_price": 0.003127923008559015}, "USDC": {"oracle": 1.000180932, "cex_price": 1, "dex_price": 1}, "USDT": {"oracle": 1.00064, "cex_price": 1, "dex_price": 1.000874095390381}}