{"json_time": 1667327490, "ETH": {"total_collateral": "0.0", "median_collateral": "nan", "top_1_collateral": "0.0", "top_10_collateral": "0.0", "total_debt": "0.0", "median_debt": "nan", "top_1_debt": "0.0", "top_10_debt": "0.0", "nl_total_collateral": "0.0", "nl_median_collateral": "nan", "nl_top_1_collateral": "0.0", "nl_top_10_collateral": "0.0", "nl_total_debt": "0.0", "nl_median_debt": "nan", "nl_top_1_debt": "0.0", "nl_top_10_debt": "0.0", "graph_data": {}}, "BNB|bsc": {"total_collateral": "0.0", "median_collateral": "nan", "top_1_collateral": "0.0", "top_10_collateral": "0.0", "total_debt": "0.0", "median_debt": "nan", "top_1_debt": "0.0", "top_10_debt": "0.0", "nl_total_collateral": "0.0", "nl_median_collateral": "nan", "nl_top_1_collateral": "0.0", "nl_top_10_collateral": "0.0", "nl_total_debt": "0.0", "nl_median_debt": "nan", "nl_top_1_debt": "0.0", "nl_top_10_debt": "0.0", "graph_data": {}}, "WBTC|eth": {"total_collateral": "0.0", "median_collateral": "nan", "top_1_collateral": "0.0", "top_10_collateral": "0.0", "total_debt": "0.0", "median_debt": "nan", "top_1_debt": "0.0", "top_10_debt": "0.0", "nl_total_collateral": "0.0", "nl_median_collateral": "nan", "nl_top_1_collateral": "0.0", "nl_top_10_collateral": "0.0", "nl_total_debt": "0.0", "nl_median_debt": "nan", "nl_top_1_debt": "0.0", "nl_top_10_debt": "0.0", "graph_data": {}}, "pCKB": {"total_collateral": "7.235530256727964", "median_collateral": "1.5701507363948228", "top_1_collateral": "3.923018703172305", "top_10_collateral": "7.235530256727963", "total_debt": "0.22069515443379847", "median_debt": "0.22069515443379847", "top_1_debt": "0.22069515443379847", "top_10_debt": "0.22069515443379847", "nl_total_collateral": "7.014835102294166", "nl_median_collateral": "1.5701507363948228", "nl_top_1_collateral": "3.702323548738507", "nl_top_10_collateral": "7.014835102294165", "nl_total_debt": "0.0", "nl_median_debt": "nan", "nl_top_1_debt": "0.0", "nl_top_10_debt": "0.0", "graph_data": {}}, "USDC": {"total_collateral": "0.250471998108", "median_collateral": "0.100025599896", "top_1_collateral": "0.149062403748", "top_10_collateral": "0.250471998108", "total_debt": "0.220173119304", "median_debt": "0.110086559652", "top_1_debt": "0.200157199368", "top_10_debt": "0.220173119304", "nl_total_collateral": "0.23045607817200003", "nl_median_collateral": "0.100025599896", "nl_top_1_collateral": "0.129046483812", "nl_top_10_collateral": "0.23045607817200003", "nl_total_debt": "0.200157199368", "nl_median_debt": "0.200157199368", "nl_top_1_debt": "0.200157199368", "nl_top_10_debt": "0.200157199368", "graph_data": {}}}